diode.cpython-39-darwin.so
diode-1.1.3.dist-info/METADATA
diode-1.1.3.dist-info/WHEEL
diode-1.1.3.dist-info/licenses/LICENSE
diode-1.1.3.dist-info/RECORD
