Metadata-Version: 2.4
Name: diode
Version: 1.1.3
Summary: alpha shape generator using CGAL
Author-Email: Dmitriy Morozov <dmitriy@mrzv.org>
License-Expression: GPL-3.0-or-later
Classifier: Development Status :: 5 - Production/Stable
Classifier: Intended Audience :: Developers
Classifier: Intended Audience :: Education
Classifier: Intended Audience :: Science/Research
Classifier: Topic :: Software Development :: Libraries :: Python Modules
Classifier: Topic :: Utilities
Classifier: Programming Language :: C++
Classifier: Programming Language :: Python :: 3.12
Project-URL: Homepage, https://github.com/mrzv/diode
Project-URL: Repository, https://github.com/mrzv/diode.git
Project-URL: Issues, https://github.com/mrzv/diode/issues
Requires-Python: >=3.9
Requires-Dist: numpy>=2
